{
  "posts": [
    {
      "writer": "게시글 테스트1",
      "password": "password_here",
      "title": "게시글 테스트1",
      "content": "게시글 테스트1게시글 테스트1",
      "id": 1,
      "created_at": "2014-03-17T14:03:17.000Z",
      "updated_at": "2023-03-22T14:50:34.467Z"
    },
    {
      "id": 2,
      "title": "제목이여기에붙어",
      "content": "내용이여기에붙어내용이여기에붙어내용이여기에붙어내용이여기에붙어내용이여기에붙어내용이여기에붙어내용이여기에붙어내용이여기에붙어내용이여기에붙어내용이여기에붙어내용이여기에붙어내용이여기에붙어내용이여기에붙어내용이여기에붙어내용이여기에붙어내용이여기에붙어내용이여기에붙어내용이여기에붙어내용이여기에붙어내용이여기에붙어내용이여기에붙어내용이여기에붙어내용이여기에붙어내용이여기에붙어내용이여기에붙어내용이여기에붙어내용이여기에붙어내용이여기에붙어내용이여기에붙어내용이여기에붙어내용이여기에붙어내용이여기에붙어내용이여기에붙어내용이여기에붙어내용이여기에붙어내용이여기에붙어내용이여기에붙어내용이여기에붙어내용이여기에붙어내용이여기에붙어내용이여기에붙어내용이여기에붙어내용이여기에붙어내용이여기에붙어내용이여기에붙어내용이여기에붙어내용이여기에붙어내용이여기에붙어내용이여기에붙어내용이여기에붙어내용이여기에붙어내용이여기에붙어내용이여기에붙어내용이여기에붙어내용이여기에붙어내용이여기에붙어내용이여기에붙어내용이여기에붙어내용이여기에붙어내용이여기에붙어내용이여기에붙어내용이여기에붙어내용이여기에붙어내용이여기에붙어내용이여기에붙어내용이여기에붙어내용이여기에붙어내용이여기에붙어내용이여기에붙어내용이여기에붙어내용이여기에붙어내용이여기에붙어내용이여기에붙어내용이여기에붙어내용이여기에붙어내용이여기에붙어내용이여기에붙어내용이여기에붙어내용이여기에붙어내용이여기에붙어내용이여기에붙어내용이여기에붙어내용이여기에붙어내용이여기에붙어내용이여기에붙어내용이여기에붙어내용이여기에붙어내용이여기에붙어내용이여기에붙어내용이여기에붙어내용이여기에붙어내용이여기에붙어내용이여기에붙어내용이여기에붙어내용이여기에붙어내용이여기에붙어내용이여기에붙어내용이여기에붙어내용이여기에붙어내용이여기에붙어내용이여기에붙어내용이여기에붙어내용이여기에붙어내용이여기에붙어내용이여기에붙어내용이여기에붙어내용이여기에붙어내용이여기에붙어내용이여기에붙어내용이여기에붙어내용이여기에붙어내용이여기에붙어내용이여기에붙어내용이여기에붙어내용이여기에붙어내용이여기에붙어내용이여기에붙어내용이여기에붙어내용이여기에붙어내용이여기에붙어내용이여기에붙어내용이여기에붙어내용이여기에붙어내용이여기에붙어내용이여기에붙어내용이여기에붙어내용이여기에붙어내용이여기에붙어내용이여기에붙어내용이여기에붙어내용이여기에붙어내용이여기에붙어내용이여기에붙어내용이여기에붙어내용이여기에붙어내용이여기에붙어내용이여기에붙어내용이여기에붙어내용이여기에붙어내용이여기에붙어내용이여기에붙어내용이여기에붙어내용이여기에붙어내용이여기에붙어내용이여기에붙어내용이여기에붙어내용이여기에붙어내용이여기에붙어내용이여기에붙어내용이여기에붙어내용이여기에붙어내용이여기에붙어내용이여기에붙어내용이여기에붙어내용이여기에붙어내용이여기에붙어내용이여기에붙어내용이여기에붙어내용이여기에붙어내용이여기에붙어내용이여기에붙어내용이여기에붙어내용이여기에붙어내용이여기에붙어내용이여기에붙어내용이여기에붙어내용이여기에붙어내용이여기에붙어내용이여기에붙어내용이여기에붙어내용이여기에붙어내용이여기에붙어내용이여기에붙어내용이여기에붙어내용이여기에붙어내용이여기에붙어내용이여기에붙어내용이여기에붙어내용이여기에붙어내용이여기에붙어내용이여기에붙어내용이여기에붙어내용이여기에붙어내용이여기에붙어내용이여기에붙어내용이여기에붙어내용이여기에붙어내용이여기에붙어내용이여기에붙어내용이여기에붙어내용이여기에붙어내용이여기에붙어내용이여기에붙어내용이여기에붙어내용이여기에붙어내용이여기에붙어내용이여기에붙어내용이여기에붙어내용이여기에붙어내용이여기에붙어",
      "writer": "글쓴이가여기에붙어",
      "password": "password_her",
      "created_at": "2016-02-23T15:02:23.000Z",
      "updated_at": "2016-02-24T15:02:24.000Z"
    },
    {
      "id": 3,
      "title": "제목이여기에붙",
      "content": "내용이여기에붙 내용이여기에붙 내용이여기에붙 내용이여기에붙 내용이여기에붙 내용이여기에붙 내용이여기에붙 내용이여기에붙 내용이여기에붙 내용이여기에붙 내용이여기에붙 내용이여기에붙 내용이여기에붙 내용이여기에붙 내용이여기에붙 내용이여기에붙 내용이여기에붙 내용이여기에붙 내용이여기에붙 내용이여기에붙 내용이여기에붙 내용이여기에붙 내용이여기에붙 내용이여기에붙 내용이여기에붙 내용이여기에붙 내용이여기에붙 내용이여기에붙 내용이여기에붙 내용이여기에붙 내용이여기에붙 내용이여기에붙 내용이여기에붙 내용이여기에붙 내용이여기에붙 내용이여기에붙 내용이여기에붙 내용이여기에붙 내용이여기에붙 내용이여기에붙 내용이여기에붙 내용이여기에붙 내용이여기에붙 내용이여기에붙 내용이여기에붙 내용이여기에붙 내용이여기에붙 내용이여기에붙 내용이여기에붙 내용이여기에붙 내용이여기에붙 내용이여기에붙 내용이여기에붙 내용이여기에붙 내용이여기에붙 내용이여기에붙 내용이여기에붙 내용이여기에붙 내용이여기에붙 내용이여기에붙 내용이여기에붙 내용이여기에붙 내용이여기에붙 내용이여기에붙 내용이여기에붙 내용이여기에붙 내용이여기에붙 내용이여기에붙 내용이여기에붙 내용이여기에붙 내용이여기에붙 내용이여기에붙 내용이여기에붙 내용이여기에붙 내용이여기에붙 내용이여기에붙 내용이여기에붙 내용이여기에붙 내용이여기에붙 내용이여기에붙 내용이여기에붙 내용이여기에붙 내용이여기에붙 내용이여기에붙 내용이여기에붙 내용이여기에붙 내용이여기에붙 내용이여기에붙 내용이여기에붙 내용이여기에붙 내용이여기에붙 내용이여기에붙 내용이여기에붙 내용이여기에붙 내용이여기에붙 내용이여기에붙 내용이여기에붙 내용이여기에붙 내용이여기에붙 내용이여기에붙 내용이여기에붙 내용이여기에붙 내용이여기에붙 내용이여기에붙 내용이여기에붙 내용이여기에붙 내용이여기에붙 내용이여기에붙 내용이여기에붙 내용이여기에붙 내용이여기에붙 내용이여기에붙 내용이여기에붙 내용이여기에붙 내용이여기에붙 내용이여기에붙 내용이여기에붙 내용이여기에붙 내용이여기에붙 내용이여기에붙 내용이여기에붙 내용이여기에붙 내용이여기에붙 내용이여기에붙 내용이여기에붙 내용이여기에붙 내용이여기에붙 내용이여기에붙 내용이여기에붙 내용이여기에붙 내용이여기에붙 내용이여기에붙 내용이여기에붙 내용이여기에붙 내용이여기에붙 내용이여기에붙 내용이여기에붙 내용이여기에붙 내용이여기에붙 내용이여기에붙 내용이여기에붙 내용이여기에붙 내용이여기에붙 내용이여기에붙 내용이여기에붙 내용이여기에붙 내용이여기에붙 내용이여기에붙 내용이여기에붙 내용이여기에붙 내용이여기에붙 내용이여기에붙 내용이여기에붙 내용이여기에붙 내용이여기에붙 내용이여기에붙 내용이여기에붙 내용이여기에붙 내용이여기에붙 내용이여기에붙 내용이여기에붙 내용이여기에붙 내용이여기에붙 내용이여기에붙 내용이여기에붙 내용이여기에붙 내용이여기에붙 내용이여기에붙 내용이여기에붙 내용이여기에붙 내용이여기에붙 내용이여기에붙 내용이여기에붙 내용이여기에붙 내용이여기에붙 내용이여기에붙 내용이여기에붙 내용이여기에붙 내용이여기에붙 내용이여기에붙 내용이여기에붙 내용이여기에붙 내용이여기에붙 내용이여기에붙 내용이여기에붙 내용이여기에붙 내용이여기에붙 내용이여기에붙 내용이여기에붙 내용이여기에붙 내용이여기에붙 내용이여기에붙 내용이여기에붙 내용이여기에붙 내용이여기에붙 내용이여기에붙 내용이여기에붙 내용이여기에붙 내용이여기에붙 내용이여기에붙 ",
      "writer": "글쓴이가여기에붙",
      "password": "password_he",
      "created_at": "2018-06-28T18:06:28.000Z",
      "updated_at": null
    },
    {
      "id": 4,
      "title": "제목이여기에",
      "content": "내용이여기에",
      "writer": "글쓴이가여기에",
      "password": "password_h",
      "created_at": "2021-02-04T21:02:04.000Z",
      "updated_at": "2021-02-06T21:02:06.000Z"
    },
    {
      "id": 5,
      "title": "제목이여기",
      "content": "내용이여기",
      "writer": "글쓴이가여기",
      "password": "password_",
      "created_at": "2021-11-09T21:11:09.000Z",
      "updated_at": null
    },
    {
      "title": "dsfgdfg",
      "content": "dfgsdfgsdfgsdfg",
      "writer": "sdfgsdfgs",
      "created_at": "2023-01-20T06:02:36.807Z",
      "updated_at": null,
      "id": 6
    },
    {
      "writer": "게시글작성1",
      "password": "asdasd",
      "title": "게시글작성1",
      "content": "게시글작성1게시글작성1게시글작성1",
      "created_at": "2023-03-22T05:14:51.880Z",
      "updated_at": null,
      "id": 7
    },
    {
      "writer": "게시글 작성 2",
      "password": "dasdasd",
      "title": "게시글 작성 2게시글 작성 2",
      "content": "게시글 작성 2게시글 작성 2게시글 작성 2게시글 작성 2게시글 작성 2",
      "created_at": "2023-03-22T05:17:41.537Z",
      "updated_at": null,
      "id": 8
    },
    {
      "writer": "게시글작성테스트5",
      "password": "sdadas",
      "title": "게시글작성테스트5게시글작성테스트5",
      "content": "게시글작성테스트5게시글작성테스트5게시글작성테스트5게시글작성테스트5게시글작성테스트5",
      "created_at": "2023-03-22T05:20:58.871Z",
      "updated_at": null,
      "id": 9
    },
    {
      "writer": "최종테스트77",
      "password": "777",
      "title": "최종테스트77",
      "content": "최종테스트77최종테스트77",
      "created_at": "2023-03-22T14:42:55.077Z",
      "updated_at": "2023-03-22T14:52:24.732Z",
      "id": 10
    },
    {
      "writer": "최종테스트88",
      "password": "111",
      "title": "최종테스트88최종테스트88",
      "content": "최종테스트88최종테스트88최종테스트88최종테스트88최종테스트88최종테스트88최종테스트88최종테스트88최종테스트88최종테스트88최종테스트88최종테스트88최종테스트88최종테스트88최종테스트88최종테스트88최종테스트88최종테스트88최종테스트88최종테스트88최종테스트88최종테스트88최종테스트88최종테스트88최종테스트88최종테스트88최종테스트88최종테스트88최종테스트88최종테스트88최종테스트88최종테스트88최종테스트88최종테스트88최종테스트88최종테스트88최종테스트88최종테스트88최종테스트88최종테스트88최종테스트88최종테스트88최종테스트88최종테스트88최종테스트88최종테스트88최종테스트88최종테스트88최종테스트88최종테스트88최종테스트88최종테스트88최종테스트88최종테스트88최종테스트88최종테스트88최종테스트88최종테스트88최종테스트88최종테스트88최종테스트88최종테스트88최종테스트88최종테스트88최종테스트88최종테스트88최종테스트88최종테스트88최종테스트88",
      "created_at": "2023-03-22T14:44:05.175Z",
      "updated_at": "2023-03-22T14:52:54.687Z",
      "id": 11
    },
    {
      "writer": "최종테스트1010",
      "password": "111",
      "title": "최종테스트1010",
      "content": "최종테스트1010",
      "created_at": "2023-03-22T14:47:06.814Z",
      "updated_at": "2023-03-22T14:53:13.792Z",
      "id": 12
    }
  ],
  "comments": [
    {
      "id": 1,
      "postId": 1,
      "parent": null,
      "content": "111",
      "writer": "111",
      "password": "password_here",
      "created_at": "2014-03-17T14:04:17.000Z",
      "updated_at": "2023-03-22T13:40:24.864Z",
      "firstComment": "333"
    },
    {
      "id": 2,
      "postId": 1,
      "parent": null,
      "content": "댓글이여기에붙어요 댓글이여기에붙어요 댓글이여기에붙어요 댓글이여기에붙어요 댓글이여기에붙어요 댓글이여기에붙어요 댓글이여기에붙어요 댓글이여기에붙어요 댓글이여기에붙어요 댓글이여기에붙어요 댓글이여기에붙어요 댓글이여기에붙어요 댓글이여기에붙어요 댓글이여기에붙어요 댓글이여기에붙어요 댓글이여기에붙어요",
      "writer": "댓쓴이가여기에붙어",
      "password": "password_her",
      "created_at": "2014-03-17T14:05:17.000Z",
      "updated_at": null
    },
    {
      "id": 3,
      "postId": 1,
      "parent": 1,
      "content": "333",
      "writer": "333",
      "password": "password_he",
      "created_at": "2014-03-17T14:06:17.000Z",
      "updated_at": "2023-03-22T13:41:10.335Z",
      "firstComment": "4444"
    },
    {
      "id": 4,
      "postId": 2,
      "parent": null,
      "content": "댓글이여기에붙어요",
      "writer": "댓쓴이가여기에붙어요",
      "password": "password_here",
      "created_at": "2016-02-24T15:02:24.000Z",
      "updated_at": null
    },
    {
      "id": 5,
      "postId": 2,
      "parent": null,
      "content": "댓글이여기에붙어요 댓글이여기에붙어요 댓글이여기에붙어요 댓글이여기에붙어요 댓글이여기에붙어요 댓글이여기에붙어요 댓글이여기에붙어요 댓글이여기에붙어요 댓글이여기에붙어요 댓글이여기에붙어요 댓글이여기에붙어요 댓글이여기에붙어요 댓글이여기에붙어요 댓글이여기에붙어요 댓글이여기에붙어요 댓글이여기에붙어요",
      "writer": "댓쓴이가여기에붙어",
      "password": "password_her",
      "created_at": "2016-02-24T15:03:24.000Z",
      "updated_at": null
    },
    {
      "id": 6,
      "postId": 2,
      "parent": 4,
      "content": "답글이여기에붙답글이여기에붙답글이여기에붙답글이여기에붙답글이여기에붙답글이여기에붙답글이여기에붙답글이여기에붙답글이여기에붙답글이여기에붙답글이여기에붙답글이여기에붙답글이여기에붙답글이여기에붙답글이여기에붙답글이여기에붙답글이여기에붙답글이여기에붙답글이여기에붙답글이여기에붙답글이여기에붙답글이여기에붙답글이여기에붙",
      "writer": "댓쓴이가여기에붙",
      "password": "password_he",
      "created_at": "2016-02-24T15:04:24.000Z",
      "updated_at": null
    },
    {
      "id": 7,
      "postId": 3,
      "parent": null,
      "content": "댓글이여기에붙어요",
      "writer": "댓쓴이가여기에붙어요",
      "password": "password_here",
      "created_at": "2018-06-28T18:06:28.000Z",
      "updated_at": null
    },
    {
      "id": 8,
      "postId": 3,
      "parent": null,
      "content": "댓글이여기에붙어요 댓글이여기에붙어요 댓글이여기에붙어요 댓글이여기에붙어요 댓글이여기에붙어요 댓글이여기에붙어요 댓글이여기에붙어요 댓글이여기에붙어요 댓글이여기에붙어요 댓글이여기에붙어요 댓글이여기에붙어요 댓글이여기에붙어요 댓글이여기에붙어요 댓글이여기에붙어요 댓글이여기에붙어요 댓글이여기에붙어요",
      "writer": "댓쓴이가여기에붙어",
      "password": "password_her",
      "created_at": "2018-06-28T18:07:28.000Z",
      "updated_at": null
    },
    {
      "id": 9,
      "postId": 3,
      "parent": 7,
      "content": "답글이여기에붙답글이여기에붙답글이여기에붙답글이여기에붙답글이여기에붙답글이여기에붙답글이여기에붙답글이여기에붙답글이여기에붙답글이여기에붙답글이여기에붙답글이여기에붙답글이여기에붙답글이여기에붙답글이여기에붙답글이여기에붙답글이여기에붙답글이여기에붙답글이여기에붙답글이여기에붙답글이여기에붙답글이여기에붙답글이여기에붙",
      "writer": "댓쓴이가여기에붙",
      "password": "password_he",
      "created_at": "2018-06-28T18:08:28.000Z",
      "updated_at": null
    },
    {
      "id": 10,
      "postId": 4,
      "parent": null,
      "content": "댓글이여기에붙어요",
      "writer": "댓쓴이가여기에붙어요",
      "password": "password_here",
      "created_at": "2021-02-04T21:02:04.000Z",
      "updated_at": null
    },
    {
      "id": 11,
      "postId": 4,
      "parent": null,
      "content": "댓글이여기에붙어요 댓글이여기에붙어요 댓글이여기에붙어요 댓글이여기에붙어요 댓글이여기에붙어요 댓글이여기에붙어요 댓글이여기에붙어요 댓글이여기에붙어요 댓글이여기에붙어요 댓글이여기에붙어요 댓글이여기에붙어요 댓글이여기에붙어요 댓글이여기에붙어요 댓글이여기에붙어요 댓글이여기에붙어요 댓글이여기에붙어요",
      "writer": "댓쓴이가여기에붙어",
      "password": "password_her",
      "created_at": "2021-02-04T21:03:04.000Z",
      "updated_at": null
    },
    {
      "id": 12,
      "postId": 4,
      "parent": 10,
      "content": "답글이여기에붙답글이여기에붙답글이여기에붙답글이여기에붙답글이여기에붙답글이여기에붙답글이여기에붙답글이여기에붙답글이여기에붙답글이여기에붙답글이여기에붙답글이여기에붙답글이여기에붙답글이여기에붙답글이여기에붙답글이여기에붙답글이여기에붙답글이여기에붙답글이여기에붙답글이여기에붙답글이여기에붙답글이여기에붙답글이여기에붙",
      "writer": "댓쓴이가여기에붙",
      "password": "password_he",
      "created_at": "2021-02-04T21:04:04.000Z",
      "updated_at": null
    },
    {
      "id": 13,
      "postId": 5,
      "parent": null,
      "content": "댓글이여기에붙어요",
      "writer": "댓쓴이가여기에붙어요",
      "password": "password_here",
      "created_at": "2021-11-09T21:12:09.000Z",
      "updated_at": null
    },
    {
      "id": 14,
      "postId": 5,
      "parent": null,
      "content": "댓글이여기에붙어요 댓글이여기에붙어요 댓글이여기에붙어요 댓글이여기에붙어요 댓글이여기에붙어요 댓글이여기에붙어요 댓글이여기에붙어요 댓글이여기에붙어요 댓글이여기에붙어요 댓글이여기에붙어요 댓글이여기에붙어요 댓글이여기에붙어요 댓글이여기에붙어요 댓글이여기에붙어요 댓글이여기에붙어요 댓글이여기에붙어요",
      "writer": "댓쓴이가여기에붙어",
      "password": "password_her",
      "created_at": "2021-11-09T21:13:09.000Z",
      "updated_at": null
    },
    {
      "id": 15,
      "postId": 5,
      "parent": 10,
      "content": "답글이여기에붙답글이여기에붙답글이여기에붙답글이여기에붙답글이여기에붙답글이여기에붙답글이여기에붙답글이여기에붙답글이여기에붙답글이여기에붙답글이여기에붙답글이여기에붙답글이여기에붙답글이여기에붙답글이여기에붙답글이여기에붙답글이여기에붙답글이여기에붙답글이여기에붙답글이여기에붙답글이여기에붙답글이여기에붙답글이여기에붙",
      "writer": "댓쓴이가여기에붙",
      "password": "password_he",
      "created_at": "2021-11-09T21:14:09.000Z",
      "updated_at": null
    },
    {
      "writer": "111",
      "password": "111",
      "content": "1111",
      "parent": null,
      "created_at": "2023-03-22T14:13:51.756Z",
      "updated_at": null,
      "id": 16
    },
    {
      "writer": "222",
      "password": "222",
      "content": "2222",
      "postId": 9,
      "parent": null,
      "created_at": "2023-03-22T14:14:56.032Z",
      "updated_at": null,
      "id": 17
    },
    {
      "writer": "111",
      "password": "111",
      "content": "111",
      "postId": 9,
      "parent": null,
      "created_at": "2023-03-22T14:17:03.424Z",
      "updated_at": null,
      "id": 18
    },
    {
      "writer": "111",
      "password": "111",
      "content": "111",
      "postId": 8,
      "parent": null,
      "created_at": "2023-03-22T14:19:09.443Z",
      "updated_at": null,
      "id": 19
    },
    {
      "writer": "222",
      "password": "222",
      "content": "222",
      "postId": 8,
      "parent": null,
      "created_at": "2023-03-22T14:19:12.912Z",
      "updated_at": null,
      "id": 20
    },
    {
      "writer": "333",
      "password": "333",
      "content": "333",
      "postId": 8,
      "parent": null,
      "created_at": "2023-03-22T14:19:17.843Z",
      "updated_at": null,
      "id": 21
    },
    {
      "writer": "111",
      "password": "22",
      "content": "1111",
      "postId": 7,
      "parent": null,
      "created_at": "2023-03-22T14:20:32.565Z",
      "updated_at": null,
      "id": 22
    },
    {
      "writer": "222",
      "password": "222",
      "content": "222",
      "postId": 7,
      "parent": null,
      "created_at": "2023-03-22T14:20:35.828Z",
      "updated_at": null,
      "id": 23
    },
    {
      "writer": "333",
      "password": "33",
      "content": "333",
      "postId": 7,
      "parent": null,
      "created_at": "2023-03-22T14:20:39.885Z",
      "updated_at": null,
      "id": 24
    },
    {
      "writer": "111",
      "password": "111",
      "content": "111",
      "postId": 6,
      "parent": null,
      "created_at": "2023-03-22T14:40:57.981Z",
      "updated_at": null,
      "id": 25
    },
    {
      "writer": "222",
      "password": "222",
      "content": "222",
      "postId": 6,
      "parent": 25,
      "created_at": "2023-03-22T14:41:05.222Z",
      "updated_at": null,
      "id": 26
    },
    {
      "writer": "333",
      "password": "333",
      "content": "333",
      "postId": 6,
      "parent": null,
      "created_at": "2023-03-22T14:41:15.877Z",
      "updated_at": null,
      "id": 27
    },
    {
      "writer": "444",
      "password": "444",
      "content": "444",
      "postId": 6,
      "parent": 25,
      "created_at": "2023-03-22T14:41:21.635Z",
      "updated_at": null,
      "id": 28
    },
    {
      "writer": "555",
      "password": "555",
      "content": "555",
      "postId": 6,
      "parent": 27,
      "created_at": "2023-03-22T14:41:30.202Z",
      "updated_at": null,
      "id": 29
    },
    {
      "writer": "777",
      "password": "777",
      "content": "777",
      "postId": 6,
      "parent": null,
      "created_at": "2023-03-22T14:41:36.142Z",
      "updated_at": null,
      "id": 30
    },
    {
      "writer": "111",
      "password": "111",
      "content": "111",
      "postId": 12,
      "parent": null,
      "created_at": "2023-03-22T14:47:41.565Z",
      "updated_at": "2023-03-22T14:48:16.775Z",
      "id": 31
    },
    {
      "writer": "222",
      "password": "222",
      "content": "222",
      "postId": 12,
      "parent": null,
      "created_at": "2023-03-22T14:47:46.345Z",
      "updated_at": null,
      "id": 32
    },
    {
      "writer": "333",
      "password": "333",
      "content": "333",
      "postId": 12,
      "parent": 31,
      "created_at": "2023-03-22T14:48:21.736Z",
      "updated_at": null,
      "id": 33
    },
    {
      "writer": "444",
      "password": "444",
      "content": "444",
      "postId": 12,
      "parent": 32,
      "created_at": "2023-03-22T14:48:27.133Z",
      "updated_at": null,
      "id": 34
    },
    {
      "writer": "222",
      "password": "555",
      "content": "222",
      "postId": 12,
      "parent": 32,
      "created_at": "2023-03-22T14:48:34.100Z",
      "updated_at": "2023-03-22T14:48:44.239Z",
      "id": 35
    },
    {
      "writer": "111",
      "password": "111",
      "content": "111",
      "postId": 5,
      "parent": 13,
      "created_at": "2023-03-22T14:51:19.620Z",
      "updated_at": null,
      "id": 36
    },
    {
      "writer": "222",
      "password": "22",
      "content": "222",
      "postId": 5,
      "parent": 13,
      "created_at": "2023-03-22T14:51:26.769Z",
      "updated_at": null,
      "id": 37
    }
  ]
}